test/__init__.py
test/mock_requests.py
test/test_api.py
test/test_base.py
test/test_exceptions.py
test/test_league.py
test/test_match.py
test/test_player.py
test/test_team.py
test/utils.py
understatapi/__init__.py
understatapi/api.py
understatapi/exceptions.py
understatapi/endpoints/__init__.py
understatapi/endpoints/base.py
understatapi/endpoints/league.py
understatapi/endpoints/match.py
understatapi/endpoints/player.py
understatapi/endpoints/team.py
understatapi-0.1.0.dist-info/METADATA
understatapi-0.1.0.dist-info/WHEEL
understatapi-0.1.0.dist-info/top_level.txt
understatapi-0.1.0.dist-info/RECORD
